{
  "allproducts": [
    {
      "id": "35",
      "productImage": "mask.jpeg",
      "productName": "Mask",
      "category": "Accesories",
      "rating": "3",
      "price": "1000",
      "inStock": "100"
    },
    {
      "id": "40",
      "productImage": "cheese.jpg",
      "productName": "Butter",
      "category": "Dairy Products",
      "rating": "4",
      "price": "300",
      "inStock": "100"
    },
    {
      "productImage": "mobile.jpg",
      "productName": "Mobile phoneeeezzzz",
      "category": "Electronics",
      "rating": "4.2",
      "price": "40000",
      "inStock": "100",
      "id": "1"
    },
    {
      "id": "2",
      "productImage": "headset.jpg",
      "productName": "Headset",
      "category": "Electronics",
      "rating": "4",
      "price": "2000",
      "inStock": "100"
    },
    {
      "id": "3",
      "productImage": "panner.jpeg",
      "productName": "Pannerr",
      "category": "Dairy Products",
      "rating": "3",
      "price": "300",
      "inStock": "100"
    },
    {
      "productImage": "gloves.jpg",
      "productName": "Glovezz",
      "category": "Accesories",
      "rating": "5",
      "price": "202",
      "inStock": "100",
      "id": "15"
    },
    {
      "productImage": "watch.jpg",
      "productName": "Digital watch",
      "category": "Electronics",
      "rating": "4",
      "price": "200",
      "inStock": "100",
      "id": "34"
    },
    {
      "id": "36",
      "productImage": "cheese.jpg",
      "productName": "Fresh cheese",
      "category": "Dairy Products",
      "rating": "4",
      "price": "200",
      "inStock": "100"
    }
  ],
  "allusers": [
    {
      "id": "test123",
      "name": "test4",
      "email": "test4@gmail.com",
      "userid": "test123",
      "pwd": "test",
      "cpwd": "test"
    },
    {
      "id": "test5",
      "name": "test5",
      "email": "test5@gmail.com",
      "userid": "test5",
      "pwd": "test@5",
      "cpwd": "test@5"
    }
  ]
}